{
  "Address": 2872393672065,
  "Name": "Col 285 Sector AU-F b12-1",
  "Population": 0,
  "LowestRecordedPopulation": 0,
  "X": 182.781250,
  "Y": 7.968750,
  "Z": -88.406250,
  "States": [
    {
      "State": "None",
      "Start": {
        "CycleNumber": 13,
        "Start": "2023-02-23T07:00:00+00:00",
        "End": "2023-03-02T07:00:00+00:00"
      },
      "End": {
        "CycleNumber": 24,
        "Start": "2023-05-11T07:00:00+00:00",
        "End": "2023-05-18T07:00:00+00:00"
      },
      "Titan": {
        "Name": "Cocijo"
      },
      "Progress": []
    },
    {
      "State": "Alert",
      "Start": {
        "CycleNumber": 25,
        "Start": "2023-05-18T07:00:00+00:00",
        "End": "2023-05-25T07:00:00+00:00"
      },
      "End": {
        "CycleNumber": 25,
        "Start": "2023-05-18T07:00:00+00:00",
        "End": "2023-05-25T07:00:00+00:00"
      },
      "Titan": {
        "Name": "Cocijo"
      },
      "Progress": [
        {
          "Progress": 0.000000,
          "Reported": "2023-05-18T11:31:29.92332+00:00",
          "Updated": "2023-05-25T06:28:35.810638+00:00"
        }
      ]
    },
    {
      "State": "Controlled",
      "Start": {
        "CycleNumber": 26,
        "Start": "2023-05-25T07:00:00+00:00",
        "End": "2023-06-01T07:00:00+00:00"
      },
      "End": {
        "CycleNumber": 29,
        "Start": "2023-06-15T07:00:00+00:00",
        "End": "2023-06-22T07:00:00+00:00"
      },
      "Titan": {
        "Name": "Cocijo"
      },
      "Progress": [
        {
          "Progress": 0.000000,
          "Reported": "2023-05-26T07:35:37.179834+00:00",
          "Updated": "2023-06-19T07:37:15.201014+00:00"
        },
        {
          "Progress": 1.000000,
          "Reported": "2023-06-20T08:36:41.091507+00:00",
          "Updated": "2023-06-20T08:36:41.091507+00:00"
        }
      ]
    },
    {
      "State": "None",
      "Start": {
        "CycleNumber": 30,
        "Start": "2023-06-22T07:00:00+00:00",
        "End": "2023-06-29T07:00:00+00:00"
      },
      "End": {
        "CycleNumber": 78,
        "Start": "2024-05-23T07:00:00+00:00",
        "End": "2024-05-30T07:00:00+00:00"
      },
      "Titan": {
        "Name": "Cocijo"
      },
      "Progress": []
    },
    {
      "State": "Alert",
      "Start": {
        "CycleNumber": 79,
        "Start": "2024-05-30T07:00:00+00:00",
        "End": "2024-06-06T07:00:00+00:00"
      },
      "End": {
        "CycleNumber": 79,
        "Start": "2024-05-30T07:00:00+00:00",
        "End": "2024-06-06T07:00:00+00:00"
      },
      "Titan": {
        "Name": "Cocijo"
      },
      "Progress": [
        {
          "Progress": 0.000000,
          "Reported": "2024-05-30T07:50:08.600393+00:00",
          "Updated": "2024-05-31T21:31:29.705039+00:00"
        },
        {
          "Progress": 0.000835,
          "Reported": "2024-05-31T21:35:30+00:00",
          "Updated": "2024-05-31T21:35:30+00:00"
        },
        {
          "Progress": 0.013448,
          "Reported": "2024-06-04T17:11:18+00:00",
          "Updated": "2024-06-04T17:50:02+00:00"
        },
        {
          "Progress": 0.024651,
          "Reported": "2024-06-04T18:14:28+00:00",
          "Updated": "2024-06-04T19:03:25+00:00"
        },
        {
          "Progress": 0.192166,
          "Reported": "2024-06-04T19:08:45+00:00",
          "Updated": "2024-06-04T19:40:45+00:00"
        },
        {
          "Progress": 0.320000,
          "Reported": "2024-06-04T20:32:54.983328+00:00",
          "Updated": "2024-06-04T20:32:54.983328+00:00"
        },
        {
          "Progress": 0.338356,
          "Reported": "2024-06-04T20:32:59+00:00",
          "Updated": "2024-06-04T20:56:16+00:00"
        },
        {
          "Progress": 0.449565,
          "Reported": "2024-06-04T21:14:08+00:00",
          "Updated": "2024-06-04T21:56:28+00:00"
        },
        {
          "Progress": 0.495383,
          "Reported": "2024-06-04T22:12:12+00:00",
          "Updated": "2024-06-04T22:56:44+00:00"
        },
        {
          "Progress": 0.641139,
          "Reported": "2024-06-04T23:08:17+00:00",
          "Updated": "2024-06-05T00:05:10+00:00"
        },
        {
          "Progress": 0.708768,
          "Reported": "2024-06-05T00:09:38+00:00",
          "Updated": "2024-06-05T00:09:38+00:00"
        },
        {
          "Progress": 0.740000,
          "Reported": "2024-06-05T01:33:14.597005+00:00",
          "Updated": "2024-06-05T01:33:14.597005+00:00"
        },
        {
          "Progress": 0.741844,
          "Reported": "2024-06-05T01:55:45+00:00",
          "Updated": "2024-06-05T02:12:55+00:00"
        },
        {
          "Progress": 0.760000,
          "Reported": "2024-06-05T02:33:14.704336+00:00",
          "Updated": "2024-06-05T02:33:14.704336+00:00"
        },
        {
          "Progress": 0.774910,
          "Reported": "2024-06-05T03:17:13+00:00",
          "Updated": "2024-06-05T03:17:13+00:00"
        },
        {
          "Progress": 0.775015,
          "Reported": "2024-06-05T03:59:56+00:00",
          "Updated": "2024-06-05T03:59:56+00:00"
        },
        {
          "Progress": 0.780000,
          "Reported": "2024-06-05T11:33:15.050321+00:00",
          "Updated": "2024-06-05T11:33:15.050321+00:00"
        },
        {
          "Progress": 0.788376,
          "Reported": "2024-06-05T12:02:56+00:00",
          "Updated": "2024-06-05T12:02:56+00:00"
        },
        {
          "Progress": 0.791328,
          "Reported": "2024-06-05T13:07:27+00:00",
          "Updated": "2024-06-05T13:51:42+00:00"
        },
        {
          "Progress": 0.805912,
          "Reported": "2024-06-05T15:17:00+00:00",
          "Updated": "2024-06-05T15:59:19+00:00"
        },
        {
          "Progress": 0.805922,
          "Reported": "2024-06-05T16:47:09+00:00",
          "Updated": "2024-06-05T17:04:52+00:00"
        },
        {
          "Progress": 0.828803,
          "Reported": "2024-06-05T17:14:11+00:00",
          "Updated": "2024-06-05T17:14:11+00:00"
        },
        {
          "Progress": 0.860000,
          "Reported": "2024-06-05T18:33:16.417109+00:00",
          "Updated": "2024-06-05T18:33:16.417109+00:00"
        },
        {
          "Progress": 0.873616,
          "Reported": "2024-06-05T18:57:15+00:00",
          "Updated": "2024-06-05T18:57:15+00:00"
        },
        {
          "Progress": 0.919059,
          "Reported": "2024-06-05T19:23:05+00:00",
          "Updated": "2024-06-05T20:00:27+00:00"
        },
        {
          "Progress": 1.000000,
          "Reported": "2024-06-05T20:33:11.054991+00:00",
          "Updated": "2024-06-05T20:33:11.054991+00:00"
        }
      ]
    },
    {
      "State": "None",
      "Start": {
        "CycleNumber": 80,
        "Start": "2024-06-06T07:00:00+00:00",
        "End": "2024-06-13T07:00:00+00:00"
      },
      "End": {
        "CycleNumber": 81,
        "Start": "2024-06-13T07:00:00+00:00",
        "End": "2024-06-20T07:00:00+00:00"
      },
      "Titan": {
        "Name": "Cocijo"
      },
      "Progress": []
    },
    {
      "State": "Alert",
      "Start": {
        "CycleNumber": 82,
        "Start": "2024-06-20T07:00:00+00:00",
        "End": "2024-06-27T07:00:00+00:00"
      },
      "End": {
        "CycleNumber": 82,
        "Start": "2024-06-20T07:00:00+00:00",
        "End": "2024-06-27T07:00:00+00:00"
      },
      "Titan": {
        "Name": "Cocijo"
      },
      "Progress": [
        {
          "Progress": 0.000000,
          "Reported": "2024-06-20T07:49:09.282857+00:00",
          "Updated": "2024-06-22T07:07:59+00:00"
        },
        {
          "Progress": 0.160000,
          "Reported": "2024-06-22T07:33:52.69214+00:00",
          "Updated": "2024-06-22T07:33:52.69214+00:00"
        },
        {
          "Progress": 0.177612,
          "Reported": "2024-06-22T08:21:37+00:00",
          "Updated": "2024-06-22T09:05:53+00:00"
        },
        {
          "Progress": 0.340000,
          "Reported": "2024-06-22T10:33:50.495386+00:00",
          "Updated": "2024-06-23T03:33:52.100244+00:00"
        },
        {
          "Progress": 0.360000,
          "Reported": "2024-06-23T04:33:59.395456+00:00",
          "Updated": "2024-06-23T04:33:59.395456+00:00"
        },
        {
          "Progress": 0.380000,
          "Reported": "2024-06-23T05:33:49.316665+00:00",
          "Updated": "2024-06-23T05:33:49.316665+00:00"
        },
        {
          "Progress": 0.420000,
          "Reported": "2024-06-23T06:33:52.281767+00:00",
          "Updated": "2024-06-23T08:33:55.455838+00:00"
        },
        {
          "Progress": 0.440000,
          "Reported": "2024-06-23T09:33:51.530441+00:00",
          "Updated": "2024-06-23T13:34:00.212342+00:00"
        },
        {
          "Progress": 0.457855,
          "Reported": "2024-06-23T13:54:37+00:00",
          "Updated": "2024-06-23T13:54:37+00:00"
        },
        {
          "Progress": 0.459823,
          "Reported": "2024-06-23T14:34:08+00:00",
          "Updated": "2024-06-23T14:37:07+00:00"
        },
        {
          "Progress": 0.460000,
          "Reported": "2024-06-23T15:34:11.358431+00:00",
          "Updated": "2024-06-23T17:34:14.116819+00:00"
        },
        {
          "Progress": 0.478622,
          "Reported": "2024-06-23T18:00:41+00:00",
          "Updated": "2024-06-23T18:09:13+00:00"
        },
        {
          "Progress": 0.480000,
          "Reported": "2024-06-23T19:34:08.480229+00:00",
          "Updated": "2024-06-23T19:34:08.480229+00:00"
        },
        {
          "Progress": 0.486492,
          "Reported": "2024-06-23T19:36:27+00:00",
          "Updated": "2024-06-23T19:46:56+00:00"
        },
        {
          "Progress": 0.680662,
          "Reported": "2024-06-23T20:04:47+00:00",
          "Updated": "2024-06-23T21:19:59+00:00"
        },
        {
          "Progress": 0.963748,
          "Reported": "2024-06-23T21:27:29+00:00",
          "Updated": "2024-06-23T21:50:37+00:00"
        },
        {
          "Progress": 0.960000,
          "Reported": "2024-06-23T21:34:11.244412+00:00",
          "Updated": "2024-06-23T21:34:11.244412+00:00"
        },
        {
          "Progress": 1.000000,
          "Reported": "2024-06-23T22:34:08.788944+00:00",
          "Updated": "2024-06-23T22:34:08.788945+00:00"
        },
        {
          "Progress": 1.556807,
          "Reported": "2024-06-24T03:47:04+00:00",
          "Updated": "2024-06-24T07:17:43+00:00"
        }
      ]
    }
  ]
}