{
  "Address": 18260992796065,
  "Name": "Pegasi Sector OI-S b4-8",
  "Population": 0,
  "LowestRecordedPopulation": 0,
  "X": -162.687500,
  "Y": -75.156250,
  "Z": -10.812500,
  "States": [
    {
      "State": "Alert",
      "Start": {
        "CycleNumber": 6,
        "Start": "2023-01-05T07:00:00+00:00",
        "End": "2023-01-12T07:00:00+00:00"
      },
      "End": {
        "CycleNumber": 6,
        "Start": "2023-01-05T07:00:00+00:00",
        "End": "2023-01-12T07:00:00+00:00"
      },
      "Titan": {
        "Name": "Raijin"
      },
      "Progress": []
    },
    {
      "State": "Controlled",
      "Start": {
        "CycleNumber": 7,
        "Start": "2023-01-12T07:00:00+00:00",
        "End": "2023-01-19T07:00:00+00:00"
      },
      "End": {
        "CycleNumber": 38,
        "Start": "2023-08-17T07:00:00+00:00",
        "End": "2023-08-24T07:00:00+00:00"
      },
      "Titan": {
        "Name": "Raijin"
      },
      "Progress": [
        {
          "Progress": 0.000000,
          "Reported": "2023-03-26T14:33:47.273125+00:00",
          "Updated": "2023-08-23T21:40:50.065015+00:00"
        },
        {
          "Progress": 1.000000,
          "Reported": "2023-08-24T01:42:48.38428+00:00",
          "Updated": "2023-08-24T01:42:48.38428+00:00"
        }
      ]
    },
    {
      "State": "None",
      "Start": {
        "CycleNumber": 39,
        "Start": "2023-08-24T07:00:00+00:00",
        "End": "2023-08-31T07:00:00+00:00"
      },
      "End": {
        "CycleNumber": 69,
        "Start": "2024-03-21T07:00:00+00:00",
        "End": "2024-03-28T07:00:00+00:00"
      },
      "Titan": {
        "Name": "Raijin"
      },
      "Progress": []
    },
    {
      "State": "Alert",
      "Start": {
        "CycleNumber": 70,
        "Start": "2024-03-28T07:00:00+00:00",
        "End": "2024-04-04T07:00:00+00:00"
      },
      "End": {
        "CycleNumber": 70,
        "Start": "2024-03-28T07:00:00+00:00",
        "End": "2024-04-04T07:00:00+00:00"
      },
      "Titan": {
        "Name": "Raijin"
      },
      "Progress": [
        {
          "Progress": 0.000000,
          "Reported": "2024-03-28T07:54:22.229272+00:00",
          "Updated": "2024-03-31T05:36:11.201692+00:00"
        },
        {
          "Progress": 0.020000,
          "Reported": "2024-03-31T06:36:17.053693+00:00",
          "Updated": "2024-04-04T06:35:33.803754+00:00"
        }
      ]
    },
    {
      "State": "Controlled",
      "Start": {
        "CycleNumber": 71,
        "Start": "2024-04-04T07:00:00+00:00",
        "End": "2024-04-11T07:00:00+00:00"
      },
      "End": {
        "CycleNumber": 91,
        "Start": "2024-08-22T07:00:00+00:00",
        "End": "2024-08-29T07:00:00+00:00"
      },
      "Titan": {
        "Name": "Raijin"
      },
      "Progress": [
        {
          "Progress": 0.000000,
          "Reported": "2024-04-04T12:49:14.731857+00:00",
          "Updated": "2024-08-24T18:42:11.744495+00:00"
        },
        {
          "Progress": 0.020000,
          "Reported": "2024-08-24T21:38:01.271108+00:00",
          "Updated": "2024-08-24T21:38:01.271108+00:00"
        },
        {
          "Progress": 0.040000,
          "Reported": "2024-08-24T22:37:34.662824+00:00",
          "Updated": "2024-08-24T22:37:34.662824+00:00"
        },
        {
          "Progress": 0.060000,
          "Reported": "2024-08-24T23:37:25.17615+00:00",
          "Updated": "2024-08-25T00:37:23.813976+00:00"
        },
        {
          "Progress": 0.080000,
          "Reported": "2024-08-25T01:37:26.075674+00:00",
          "Updated": "2024-08-25T01:37:26.075674+00:00"
        },
        {
          "Progress": 0.100000,
          "Reported": "2024-08-25T02:37:24.697572+00:00",
          "Updated": "2024-08-25T03:37:08.522855+00:00"
        },
        {
          "Progress": 0.120000,
          "Reported": "2024-08-25T04:37:07.756864+00:00",
          "Updated": "2024-08-25T04:37:07.756864+00:00"
        },
        {
          "Progress": 0.140000,
          "Reported": "2024-08-25T05:37:05.171701+00:00",
          "Updated": "2024-08-25T06:37:13.144591+00:00"
        },
        {
          "Progress": 0.160000,
          "Reported": "2024-08-25T07:37:03.041314+00:00",
          "Updated": "2024-08-25T08:37:13.765677+00:00"
        },
        {
          "Progress": 0.177679,
          "Reported": "2024-08-25T08:40:19+00:00",
          "Updated": "2024-08-25T08:40:19+00:00"
        },
        {
          "Progress": 0.180000,
          "Reported": "2024-08-25T09:37:12.530115+00:00",
          "Updated": "2024-08-25T10:37:14.63404+00:00"
        },
        {
          "Progress": 0.200000,
          "Reported": "2024-08-25T11:37:06.643161+00:00",
          "Updated": "2024-08-25T12:23:47.615726+00:00"
        },
        {
          "Progress": 0.220000,
          "Reported": "2024-08-25T14:29:17.135367+00:00",
          "Updated": "2024-08-25T14:29:17.135367+00:00"
        },
        {
          "Progress": 0.240000,
          "Reported": "2024-08-25T15:37:52.421489+00:00",
          "Updated": "2024-08-25T15:37:52.421489+00:00"
        },
        {
          "Progress": 0.280000,
          "Reported": "2024-08-25T16:37:51.122188+00:00",
          "Updated": "2024-08-25T16:37:51.122188+00:00"
        },
        {
          "Progress": 0.300000,
          "Reported": "2024-08-25T17:37:49.974167+00:00",
          "Updated": "2024-08-25T17:37:49.974167+00:00"
        },
        {
          "Progress": 0.340000,
          "Reported": "2024-08-25T19:35:36.213174+00:00",
          "Updated": "2024-08-25T19:35:36.213174+00:00"
        },
        {
          "Progress": 0.360000,
          "Reported": "2024-08-25T20:35:41.574657+00:00",
          "Updated": "2024-08-25T20:35:41.574657+00:00"
        },
        {
          "Progress": 0.380000,
          "Reported": "2024-08-25T21:35:48.831953+00:00",
          "Updated": "2024-08-25T21:35:48.831953+00:00"
        },
        {
          "Progress": 0.400000,
          "Reported": "2024-08-25T22:35:52.042579+00:00",
          "Updated": "2024-08-25T22:35:52.042579+00:00"
        },
        {
          "Progress": 0.420000,
          "Reported": "2024-08-25T23:36:00.512301+00:00",
          "Updated": "2024-08-25T23:36:00.512301+00:00"
        },
        {
          "Progress": 0.440000,
          "Reported": "2024-08-26T00:36:13.532998+00:00",
          "Updated": "2024-08-26T00:36:13.532998+00:00"
        },
        {
          "Progress": 0.460000,
          "Reported": "2024-08-26T01:35:58.171372+00:00",
          "Updated": "2024-08-26T01:35:58.171372+00:00"
        },
        {
          "Progress": 0.480000,
          "Reported": "2024-08-26T02:36:00.26766+00:00",
          "Updated": "2024-08-26T03:35:51.352186+00:00"
        },
        {
          "Progress": 0.500000,
          "Reported": "2024-08-26T04:35:51.509681+00:00",
          "Updated": "2024-08-26T04:35:51.509681+00:00"
        },
        {
          "Progress": 0.520000,
          "Reported": "2024-08-26T05:35:58.928344+00:00",
          "Updated": "2024-08-26T06:35:53.058107+00:00"
        },
        {
          "Progress": 0.540000,
          "Reported": "2024-08-26T07:35:49.068239+00:00",
          "Updated": "2024-08-26T11:34:40.591346+00:00"
        },
        {
          "Progress": 0.560000,
          "Reported": "2024-08-26T12:34:39.804153+00:00",
          "Updated": "2024-08-26T13:34:38.160768+00:00"
        },
        {
          "Progress": 0.582831,
          "Reported": "2024-08-26T14:18:44+00:00",
          "Updated": "2024-08-26T14:18:44+00:00"
        },
        {
          "Progress": 0.580000,
          "Reported": "2024-08-26T14:34:42.009458+00:00",
          "Updated": "2024-08-26T14:34:42.009458+00:00"
        },
        {
          "Progress": 0.600000,
          "Reported": "2024-08-26T15:34:42.291631+00:00",
          "Updated": "2024-08-26T15:34:42.291631+00:00"
        },
        {
          "Progress": 0.620000,
          "Reported": "2024-08-26T16:34:44.569497+00:00",
          "Updated": "2024-08-26T17:34:55.742781+00:00"
        },
        {
          "Progress": 0.640000,
          "Reported": "2024-08-26T18:34:41.897093+00:00",
          "Updated": "2024-08-26T18:34:41.897093+00:00"
        },
        {
          "Progress": 0.660000,
          "Reported": "2024-08-26T19:34:43.020399+00:00",
          "Updated": "2024-08-26T19:34:43.020399+00:00"
        },
        {
          "Progress": 0.680000,
          "Reported": "2024-08-26T20:34:47.862514+00:00",
          "Updated": "2024-08-26T20:34:47.862514+00:00"
        },
        {
          "Progress": 0.700000,
          "Reported": "2024-08-26T21:34:43.550969+00:00",
          "Updated": "2024-08-26T21:34:43.550969+00:00"
        },
        {
          "Progress": 0.708698,
          "Reported": "2024-08-26T22:28:38+00:00",
          "Updated": "2024-08-26T22:28:38+00:00"
        },
        {
          "Progress": 0.720000,
          "Reported": "2024-08-26T23:34:40.456838+00:00",
          "Updated": "2024-08-27T00:34:38.248876+00:00"
        },
        {
          "Progress": 0.740000,
          "Reported": "2024-08-27T01:34:38.251918+00:00",
          "Updated": "2024-08-27T02:34:35.355685+00:00"
        },
        {
          "Progress": 0.752880,
          "Reported": "2024-08-27T02:42:13+00:00",
          "Updated": "2024-08-27T02:42:13+00:00"
        },
        {
          "Progress": 0.760000,
          "Reported": "2024-08-27T04:34:39.528306+00:00",
          "Updated": "2024-08-27T04:34:39.528306+00:00"
        },
        {
          "Progress": 0.761792,
          "Reported": "2024-08-27T05:26:02+00:00",
          "Updated": "2024-08-27T05:26:02+00:00"
        },
        {
          "Progress": 0.764393,
          "Reported": "2024-08-27T05:55:33+00:00",
          "Updated": "2024-08-27T05:55:33+00:00"
        },
        {
          "Progress": 0.780000,
          "Reported": "2024-08-27T10:34:42.022385+00:00",
          "Updated": "2024-08-27T12:34:43.237613+00:00"
        },
        {
          "Progress": 0.800000,
          "Reported": "2024-08-27T13:34:46.328084+00:00",
          "Updated": "2024-08-27T14:34:36.885485+00:00"
        },
        {
          "Progress": 0.804860,
          "Reported": "2024-08-27T14:59:45+00:00",
          "Updated": "2024-08-27T14:59:45+00:00"
        },
        {
          "Progress": 0.819425,
          "Reported": "2024-08-27T16:28:05+00:00",
          "Updated": "2024-08-27T16:28:05+00:00"
        },
        {
          "Progress": 0.831475,
          "Reported": "2024-08-27T17:17:31+00:00",
          "Updated": "2024-08-27T18:04:57+00:00"
        },
        {
          "Progress": 0.842620,
          "Reported": "2024-08-27T18:24:35+00:00",
          "Updated": "2024-08-27T18:37:54+00:00"
        },
        {
          "Progress": 0.859852,
          "Reported": "2024-08-27T19:08:11+00:00",
          "Updated": "2024-08-27T20:11:10+00:00"
        },
        {
          "Progress": 0.903628,
          "Reported": "2024-08-27T20:31:20+00:00",
          "Updated": "2024-08-27T20:45:19+00:00"
        },
        {
          "Progress": 0.953153,
          "Reported": "2024-08-27T21:10:08+00:00",
          "Updated": "2024-08-27T21:50:17+00:00"
        },
        {
          "Progress": 0.980000,
          "Reported": "2024-08-27T22:34:31.119463+00:00",
          "Updated": "2024-08-27T22:34:31.119463+00:00"
        },
        {
          "Progress": 1.000000,
          "Reported": "2024-08-27T23:34:35.003186+00:00",
          "Updated": "2024-08-27T23:34:35.003186+00:00"
        },
        {
          "Progress": 1.004206,
          "Reported": "2024-08-28T05:24:47+00:00",
          "Updated": "2024-08-28T05:24:47+00:00"
        }
      ]
    }
  ]
}